hkube_python_wrapper/__init__.py
hkube_python_wrapper/__version__.py
hkube_python_wrapper/cache/__init__.py
hkube_python_wrapper/cache/caching.py
hkube_python_wrapper/codeApi/__init__.py
hkube_python_wrapper/codeApi/execution.py
hkube_python_wrapper/codeApi/hkube_api.py
hkube_python_wrapper/codeApi/waitFor.py
hkube_python_wrapper/communication/DataRequest.py
hkube_python_wrapper/communication/DataServer.py
hkube_python_wrapper/communication/__init__.py
hkube_python_wrapper/communication/streaming/MessageListener.py
hkube_python_wrapper/communication/streaming/MessageProducer.py
hkube_python_wrapper/communication/streaming/StreamingListener.py
hkube_python_wrapper/communication/streaming/StreamingManager.py
hkube_python_wrapper/communication/streaming/__init__.py
hkube_python_wrapper/communication/zmq/ZMQPingServer.py
hkube_python_wrapper/communication/zmq/ZMQRequest.py
hkube_python_wrapper/communication/zmq/ZMQServer.py
hkube_python_wrapper/communication/zmq/ZMQServers.py
hkube_python_wrapper/communication/zmq/__init__.py
hkube_python_wrapper/communication/zmq/consts.py
hkube_python_wrapper/communication/zmq/streaming/ZMQListener.py
hkube_python_wrapper/communication/zmq/streaming/__init__.py
hkube_python_wrapper/communication/zmq/streaming/signals.py
hkube_python_wrapper/communication/zmq/streaming/producer/Flow.py
hkube_python_wrapper/communication/zmq/streaming/producer/MessageQueue.py
hkube_python_wrapper/communication/zmq/streaming/producer/ZMQProducer.py
hkube_python_wrapper/communication/zmq/streaming/producer/__init__.py
hkube_python_wrapper/config/__init__.py
hkube_python_wrapper/config/config.py
hkube_python_wrapper/storage/__init__.py
hkube_python_wrapper/storage/base_storage_manager.py
hkube_python_wrapper/storage/fs_adapter.py
hkube_python_wrapper/storage/s3_adapter.py
hkube_python_wrapper/storage/storage_manager.py
hkube_python_wrapper/storage/task_output_manager.py
hkube_python_wrapper/tracing/__init__.py
hkube_python_wrapper/tracing/tracer.py
hkube_python_wrapper-2.4.2.dist-info/LICENSE
hkube_python_wrapper-2.4.2.dist-info/METADATA
hkube_python_wrapper-2.4.2.dist-info/WHEEL
hkube_python_wrapper-2.4.2.dist-info/top_level.txt
hkube_python_wrapper-2.4.2.dist-info/RECORD
