Metadata-Version: 2.1
Name: hkube-python-wrapper
Version: 2.4.2
Summary: Hkube Python Wrapper
Home-page: https://github.com/kube-HPC/python-wrapper.hkube
Author: Hkube
Author-email: hkube.dev@gmail.com
License: MIT
Platform: UNKNOWN
Classifier: Programming Language :: Python :: 3
Classifier: License :: OSI Approved :: MIT License
Classifier: Operating System :: OS Independent
Requires-Dist: Events (==0.4)
Requires-Dist: websocket-client (==0.57.0)
Requires-Dist: simplejson (==3.17.2)
Requires-Dist: pymongo (==3.11.3)
Requires-Dist: msgpack (==1.0.2)
Requires-Dist: boto3 (<=1.17.20)
Requires-Dist: wsaccel (==0.6.2)
Requires-Dist: six (==1.15.0)
Requires-Dist: pyzmq (<=22.0.3)
Requires-Dist: pympler (==0.9)
Requires-Dist: jaeger-client (==4.0.0) ; python_version < "3.2.0"
Requires-Dist: jaeger-client (>=4.4.0) ; python_version >= "3.2.0"
